game_generators/__init__.py
game_generators/functions/__init__.py
game_generators/functions/ces.py
game_generators/functions/cobb_douglas.py
game_generators/functions/concave.py
game_generators/functions/interpolate.py
game_generators/functions/leontief.py
game_generators/functions/linear.py
game_generators/functions/monotonic.py
game_generators/functions/polynomial.py
game_generators/multi_objective/__init__.py
game_generators/multi_objective/from_nfg.py
game_generators/multi_objective/identity.py
game_generators/nfg/__init__.py
game_generators/nfg/bach_stravinsky.py
game_generators/nfg/bertrand_oligopoly.py
game_generators/nfg/chicken.py
game_generators/nfg/congestion.py
game_generators/nfg/covariant.py
game_generators/nfg/discrete_uniform.py
game_generators/nfg/grab_the_dollar.py
game_generators/nfg/hawk_dove.py
game_generators/nfg/majority_voting.py
game_generators/nfg/potential.py
game_generators/nfg/random_uniform.py
game_generators/nfg/war_of_attrition.py
game_generators/nfg/zero_sum.py
game_generators/utils/__init__.py
game_generators/utils/data.py
game_generators/utils/generators.py
game_generators/utils/transforms.py
game_generators/utils/visualisation.py
game_generators-0.1.6.dist-info/LICENSE
game_generators-0.1.6.dist-info/METADATA
game_generators-0.1.6.dist-info/WHEEL
game_generators-0.1.6.dist-info/RECORD
