Metadata-Version: 2.1
Name: game-generators
Version: 0.1.6
Summary: Efficiently generate games for research and experimentation
Home-page: https://github.com/wilrop/game-generators
License: MIT
Author: Willem Röpke
Author-email: willem.ropke@vub.be
Requires-Python: >=3.10,<4.0
Classifier: License :: OSI Approved :: MIT License
Classifier: Programming Language :: Python :: 3
Classifier: Programming Language :: Python :: 3.10
Classifier: Programming Language :: Python :: 3.11
Classifier: Programming Language :: Python :: 3.12
Requires-Dist: matplotlib (>=3.8.1,<4.0.0)
Requires-Dist: numpy (>=1.26.2,<2.0.0)
Requires-Dist: scipy (==1.11.3) ; python_version < "3.13"
Project-URL: Repository, https://github.com/wilrop/game-generators
